{
  "PID": {
    "1":  { "name": "Set ID - PID", "datatype": "SI" },
    "2":  { "name": "Patient ID", "datatype": "CX" },
    "3":  { "name": "Patient Identifier List", "datatype": "CX" },
    "4":  { "name": "Alternate Patient ID - PID", "datatype": "CX" },
    "5":  { "name": "Patient Name", "datatype": "XPN" },
    "6":  { "name": "Mother's Maiden Name", "datatype": "XPN" },
    "7":  { "name": "Date/Time of Birth", "datatype": "TS" },
    "8":  { "name": "Administrative Sex", "datatype": "IS" },
    "9":  { "name": "Patient Alias", "datatype": "XPN" },
    "10": { "name": "Race", "datatype": "CE" },
    "11": { "name": "Patient Address", "datatype": "XAD" },
    "12": { "name": "County Code", "datatype": "IS" },
    "13": { "name": "Phone Number - Home", "datatype": "XTN" },
    "14": { "name": "Phone Number - Business", "datatype": "XTN" },
    "15": { "name": "Primary Language", "datatype": "CE" },
    "16": { "name": "Marital Status", "datatype": "CE" },
    "17": { "name": "Religion", "datatype": "CE" },
    "18": { "name": "Patient Account Number", "datatype": "CX" },
    "19": { "name": "SSN Number - Patient", "datatype": "ST" },
    "20": { "name": "Driver's License Number - Patient", "datatype": "DLN" },
    "21": { "name": "Mother's Identifier", "datatype": "CX" },
    "22": { "name": "Ethnic Group", "datatype": "CE" },
    "23": { "name": "Birth Place", "datatype": "ST" },
    "24": { "name": "Multiple Birth Indicator", "datatype": "ID" },
    "25": { "name": "Birth Order", "datatype": "NM" },
    "26": { "name": "Citizenship", "datatype": "CE" },
    "27": { "name": "Veterans Military Status", "datatype": "CE" },
    "28": { "name": "Nationality", "datatype": "CE" },
    "29": { "name": "Patient Death Date and Time", "datatype": "TS" },
    "30": { "name": "Patient Death Indicator", "datatype": "ID" },
    "31": { "name": "Identity Unknown Indicator", "datatype": "ID" },
    "32": { "name": "Identity Reliability Code", "datatype": "IS" },
    "33": { "name": "Last Update Date/Time", "datatype": "TS" },
    "34": { "name": "Last Update Facility", "datatype": "HD" },
    "35": { "name": "Species Code", "datatype": "CE" },
    "36": { "name": "Breed Code", "datatype": "CE" },
    "37": { "name": "Strain", "datatype": "ST" },
    "38": { "name": "Production Class Code", "datatype": "CE" },
    "39": { "name": "Tribal Citizenship", "datatype": "CWE" }
  }
}
